optimus_dl/__init__.py
optimus_dl/_version.py
optimus_dl/py.typed
optimus_dl/core/__init__.py
optimus_dl/core/bootstrap.py
optimus_dl/core/device.py
optimus_dl/core/env.py
optimus_dl/core/log.py
optimus_dl/core/model_utils.py
optimus_dl/core/omegaconf.py
optimus_dl/core/profile.py
optimus_dl/core/registry.py
optimus_dl/modules/__init__.py
optimus_dl/modules/checkpoint/__init__.py
optimus_dl/modules/checkpoint/checkpoint_manager.py
optimus_dl/modules/checkpoint/load_strategy.py
optimus_dl/modules/criterion/__init__.py
optimus_dl/modules/criterion/base.py
optimus_dl/modules/criterion/config.py
optimus_dl/modules/criterion/cross_entropy.py
optimus_dl/modules/data/__init__.py
optimus_dl/modules/data/config.py
optimus_dl/modules/data/datasets/__init__.py
optimus_dl/modules/data/datasets/base.py
optimus_dl/modules/data/datasets/composite.py
optimus_dl/modules/data/datasets/huggingface.py
optimus_dl/modules/data/datasets/loop_dataset.py
optimus_dl/modules/data/datasets/tokenized_dataset.py
optimus_dl/modules/data/datasets/tokenized_flat_dataset.py
optimus_dl/modules/data/datasets/txt_lines.py
optimus_dl/modules/data/presets/__init__.py
optimus_dl/modules/data/presets/fineweb-edu.py
optimus_dl/modules/data/presets/slimpajama.py
optimus_dl/modules/data/presets/tinyshakespeare.py
optimus_dl/modules/data/transforms/__init__.py
optimus_dl/modules/data/transforms/base.py
optimus_dl/modules/data/transforms/chunk_tokens.py
optimus_dl/modules/data/transforms/composite.py
optimus_dl/modules/data/transforms/flat_tokens_batcher.py
optimus_dl/modules/data/transforms/prefetch.py
optimus_dl/modules/data/transforms/shuffle.py
optimus_dl/modules/data/transforms/to_device.py
optimus_dl/modules/data/transforms/tokenize.py
optimus_dl/modules/distributed/__init__.py
optimus_dl/modules/distributed/base.py
optimus_dl/modules/distributed/config.py
optimus_dl/modules/distributed/fake.py
optimus_dl/modules/distributed/mesh.py
optimus_dl/modules/eval/__init__.py
optimus_dl/modules/eval/model.py
optimus_dl-0.0.7.dist-info/licenses/LICENSE
optimus_dl-0.0.7.dist-info/METADATA
optimus_dl-0.0.7.dist-info/WHEEL
optimus_dl-0.0.7.dist-info/entry_points.txt
optimus_dl-0.0.7.dist-info/top_level.txt
optimus_dl-0.0.7.dist-info/RECORD
