Metadata-Version: 2.4
Name: optimus-dl
Version: 0.0.7
Summary: A clean, modular framework for training large language models with modern PyTorch features
Author-email: Alex Dremov <dremov.me@gmail.com>
Maintainer-email: Alex Dremov <dremov.me@gmail.com>
License: MIT
Project-URL: Homepage, https://github.com/alexdremov/optimus-dl
Project-URL: Repository, https://github.com/alexdremov/optimus-dl
Project-URL: Documentation, https://github.com/alexdremov/optimus-dl#readme
Project-URL: Bug Tracker, https://github.com/alexdremov/optimus-dl.git/issues
Keywords: machine-learning,deep-learning,pytorch,llm,transformer,training,nlp
Classifier: Development Status :: 3 - Alpha
Classifier: Intended Audience :: Developers
Classifier: Intended Audience :: Science/Research
Classifier: License :: OSI Approved :: MIT License
Classifier: Operating System :: OS Independent
Classifier: Programming Language :: Python :: 3
Classifier: Programming Language :: Python :: 3.10
Classifier: Programming Language :: Python :: 3.11
Classifier: Topic :: Scientific/Engineering :: Artificial Intelligence
Classifier: Topic :: Software Development :: Libraries :: Python Modules
Requires-Python: <3.14,>=3.11
License-File: LICENSE
Requires-Dist: click>=8.2.1
Requires-Dist: colorlog>=6.9.0
Requires-Dist: datasets>=4.0.0
Requires-Dist: hydra-core>=1.3.2
Requires-Dist: liger-kernel>=0.6.4; sys_platform == "linux"
Requires-Dist: lm-eval>=0.4.9
Requires-Dist: omegaconf>=2.3.0
Requires-Dist: pydantic>=2.12.5
Requires-Dist: pyyaml>=6.0.3
Requires-Dist: rich>=13.7.0
Requires-Dist: tiktoken>=0.9.0
Requires-Dist: torch>=2.7.0
Requires-Dist: torchdata>=0.11.0
Requires-Dist: torcheval>=0.0.7
Requires-Dist: tqdm>=4.67.1
Requires-Dist: transformers>=4.53.2
Requires-Dist: wandb>=0.21.0
Requires-Dist: zstandard>=0.23.0
Provides-Extra: docs
Requires-Dist: mkdocs>=1.5.0; extra == "docs"
Requires-Dist: mkdocs-material>=9.5.0; extra == "docs"
Requires-Dist: mkdocstrings[python]>=0.24.0; extra == "docs"
Requires-Dist: mkdocs-gen-files>=0.5.0; extra == "docs"
Requires-Dist: mkdocs-literate-nav>=0.6.0; extra == "docs"
Requires-Dist: griffe-fieldz>=0.4.0; extra == "docs"
Provides-Extra: notebook
Requires-Dist: ipython>=8.37.0; extra == "notebook"
Requires-Dist: jupyter>=1.1.0; extra == "notebook"
Requires-Dist: matplotlib>=3.9.0; extra == "notebook"
Requires-Dist: seaborn>=0.13.0; extra == "notebook"
Provides-Extra: dev
Requires-Dist: black>=25.1.0; extra == "dev"
Requires-Dist: ipython>=8.37.0; extra == "dev"
Requires-Dist: isort>=6.0.1; extra == "dev"
Requires-Dist: pytest>=8.4.1; extra == "dev"
Requires-Dist: ruff>=0.14.10; extra == "dev"
Requires-Dist: pytest-xdist>=3.6.0; extra == "dev"
Dynamic: license-file
